voxy/__init__.py
voxy/base.py
voxy-0.0.3.dist-info/LICENSE
voxy-0.0.3.dist-info/METADATA
voxy-0.0.3.dist-info/WHEEL
voxy-0.0.3.dist-info/top_level.txt
voxy-0.0.3.dist-info/RECORD
