Metadata-Version: 2.2
Name: voxy
Version: 0.0.3
Summary: Facade for voice cloning and speech synthesis
Home-page: https://github.com/thorwhalen/voxy
Author: Thor Whalen
License: mit
Platform: any
License-File: LICENSE
